agentgear/__init__.py
agentgear/version.py
agentgear/cli/__init__.py
agentgear/cli/main.py
agentgear/sdk/__init__.py
agentgear/sdk/client.py
agentgear/sdk/decorators.py
agentgear/sdk/prompt.py
agentgear/sdk/trace.py
agentgear/sdk/integrations/openai.py
agentgear/server/__init__.py
agentgear/server/app/__init__.py
agentgear/server/app/auth.py
agentgear/server/app/config.py
agentgear/server/app/db.py
agentgear/server/app/deps.py
agentgear/server/app/main.py
agentgear/server/app/migrations.py
agentgear/server/app/models.py
agentgear/server/app/schemas.py
agentgear/server/app/api/__init__.py
agentgear/server/app/api/auth.py
agentgear/server/app/api/datasets.py
agentgear/server/app/api/evaluations.py
agentgear/server/app/api/evaluators.py
agentgear/server/app/api/git_ops.py
agentgear/server/app/api/llm_models.py
agentgear/server/app/api/metrics.py
agentgear/server/app/api/projects.py
agentgear/server/app/api/prompts.py
agentgear/server/app/api/runs.py
agentgear/server/app/api/seed.py
agentgear/server/app/api/settings.py
agentgear/server/app/api/spans.py
agentgear/server/app/api/tokens.py
agentgear/server/app/api/users.py
agentgear/server/app/utils/email.py
agentgear/server/app/utils/llm.py
agentgear/server/static/index.html
agentgear/server/static/assets/index-BeICao-P.css
agentgear/server/static/assets/index-b66rPyzO.js
agentgear_ai-0.1.19.dist-info/METADATA
agentgear_ai-0.1.19.dist-info/WHEEL
agentgear_ai-0.1.19.dist-info/entry_points.txt
agentgear_ai-0.1.19.dist-info/licenses/LICENSE
agentgear_ai-0.1.19.dist-info/RECORD
