Metadata-Version: 2.4
Name: agentgear-ai
Version: 0.1.19
Summary: AgentGear: LLM observability, prompt management, and agentic tracing platform with SDK, FastAPI backend, and dashboard.
Project-URL: Homepage, https://github.com/debpanda/agentgear
Project-URL: Repository, https://github.com/debpanda/agentgear
Project-URL: Issues, https://github.com/debpanda/agentgear/issues
Author: AgentGear Contributors
License-Expression: Apache-2.0
License-File: LICENSE
Keywords: agents,fastapi,llm,observability,prompts,sdk,tracing
Classifier: Framework :: FastAPI
Classifier: License :: OSI Approved :: Apache Software License
Classifier: Programming Language :: Python
Classifier: Programming Language :: Python :: 3
Classifier: Programming Language :: Python :: 3.10
Classifier: Programming Language :: Python :: 3.11
Classifier: Programming Language :: Python :: 3.12
Classifier: Topic :: Software Development :: Libraries
Requires-Python: >=3.10
Requires-Dist: fastapi>=0.110
Requires-Dist: httpx>=0.27
Requires-Dist: itsdangerous>=2.2
Requires-Dist: jinja2>=3.1
Requires-Dist: pydantic-settings>=2.0
Requires-Dist: pydantic>=2.6
Requires-Dist: python-dateutil>=2.8
Requires-Dist: python-multipart>=0.0.9
Requires-Dist: pyyaml>=6.0
Requires-Dist: requests>=2.31
Requires-Dist: sqlalchemy>=2.0
Requires-Dist: typer>=0.9
Requires-Dist: uvicorn[standard]>=0.27
Provides-Extra: cli
Requires-Dist: typer[all]>=0.9; extra == 'cli'
Provides-Extra: dev
Requires-Dist: coverage>=7.4; extra == 'dev'
Requires-Dist: mypy>=1.8; extra == 'dev'
Requires-Dist: pytest-asyncio>=0.23; extra == 'dev'
Requires-Dist: pytest>=7.4; extra == 'dev'
Requires-Dist: ruff>=0.3; extra == 'dev'
Requires-Dist: types-python-dateutil; extra == 'dev'
Provides-Extra: server
Requires-Dist: uvicorn[standard]>=0.27; extra == 'server'
